ulearn_scoring/__init__.py
ulearn_scoring/_common.py
ulearn_scoring/_config.py
ulearn_scoring/_di.py
ulearn_scoring/_models.py
ulearn_scoring/_modules.py
ulearn_scoring/_readers.py
ulearn_scoring/_scoring.py
ulearn_scoring/_storages.py
ulearn_scoring/_typing.py
ulearn_scoring/_writers.py
ulearn_scoring/cli.py
ulearn_scoring-0.2.1.dist-info/LICENSE
ulearn_scoring-0.2.1.dist-info/METADATA
ulearn_scoring-0.2.1.dist-info/WHEEL
ulearn_scoring-0.2.1.dist-info/entry_points.txt
ulearn_scoring-0.2.1.dist-info/top_level.txt
ulearn_scoring-0.2.1.dist-info/RECORD
