Metadata-Version: 2.1
Name: ulearn-scoring
Version: 0.2.1
Summary: Scoring of statements in ulearn by weeks
Home-page: https://github.com/daniel55411/ulearn-scoring
Author: zhenikhov d.k.
License: Apache License, Version 2.0
Project-URL: Issues, https://github.com/daniel55411/ulearn-scoring/issues
Project-URL: CI, https://github.com/daniel55411/ulearn-scoring/actions
Project-URL: Changelog, https://github.com/daniel55411/ulearn-scoring/releases
Platform: UNKNOWN
Requires-Python: >=3.6
License-File: LICENSE
Requires-Dist: click (<9.0.0,>=8.0.1)
Requires-Dist: pydantic-yaml[ruamel] (<1.0.0,>=0.6.0)
Requires-Dist: openpyxl (<4.0.0,>=3.0.0)
Requires-Dist: punq
Requires-Dist: ujson
Requires-Dist: pydantic
Provides-Extra: test
Requires-Dist: pytest ; extra == 'test'
Requires-Dist: pytest-mock ; extra == 'test'
